curseforge_api_wrapper/__init__.py
curseforge_api_wrapper/client.py
curseforge_api_wrapper/expections.py
curseforge_api_wrapper/models.py
curseforge_api_wrapper/network.py
curseforge_api_wrapper-1.0.1.dist-info/METADATA
curseforge_api_wrapper-1.0.1.dist-info/WHEEL
curseforge_api_wrapper-1.0.1.dist-info/licenses/LICENSE
curseforge_api_wrapper-1.0.1.dist-info/RECORD
